corva_data_assets/__init__.py
corva_data_assets/api_client.py
corva_data_assets/api_response.py
corva_data_assets/configuration.py
corva_data_assets/exceptions.py
corva_data_assets/py.typed
corva_data_assets/rest.py
corva_data_assets/api/__init__.py
corva_data_assets/api/corva_assets_api.py
corva_data_assets/models/__init__.py
corva_data_assets/models/corva_asset.py
corva_data_assets/models/corva_asset_program.py
corva_data_assets/models/corva_asset_program_id.py
corva_data_assets/models/corva_asset_rig.py
corva_data_assets/models/corva_asset_rig_id.py
corva_data_assets/models/corva_asset_stats.py
corva_data_assets/models/corva_asset_top_hole.py
corva_data_assets/models/http_validation_error.py
corva_data_assets-1.0.2.dist-info/METADATA
corva_data_assets-1.0.2.dist-info/WHEEL
corva_data_assets-1.0.2.dist-info/top_level.txt
corva_data_assets-1.0.2.dist-info/RECORD
