Metadata-Version: 2.1
Name: corva-data-assets
Version: 1.0.2
Summary: Corva Data API
Home-page: 
Author: Tung Nguyen
Author-email: tungnq@gmail.com
Keywords: OpenAPI,OpenAPI-Generator,Corva Data API
Requires-Dist: urllib3 <2.1.0,>=1.25.3
Requires-Dist: python-dateutil
Requires-Dist: pydantic <2,>=1.10.5
Requires-Dist: aenum
